{
  "id": "2ac7a51d-5fb4-45dc-9819-6cec073ceab1",
  "prevId": "00000000-0000-0000-0000-000000000000",
  "version": "7",
  "dialect": "postgresql",
  "tables": {
    "public.appointments": {
      "name": "appointments",
      "schema": "",
      "columns": {
        "id": {
          "name": "id",
          "type": "uuid",
          "primaryKey": true,
          "notNull": true,
          "default": "gen_random_uuid()"
        },
        "client_id": {
          "name": "client_id",
          "type": "uuid",
          "primaryKey": false,
          "notNull": true
        },
        "barber_id": {
          "name": "barber_id",
          "type": "uuid",
          "primaryKey": false,
          "notNull": true
        },
        "service_id": {
          "name": "service_id",
          "type": "uuid",
          "primaryKey": false,
          "notNull": true
        },
        "date": {
          "name": "date",
          "type": "date",
          "primaryKey": false,
          "notNull": true
        },
        "start_time": {
          "name": "start_time",
          "type": "time",
          "primaryKey": false,
          "notNull": true
        },
        "end_time": {
          "name": "end_time",
          "type": "time",
          "primaryKey": false,
          "notNull": true
        },
        "status": {
          "name": "status",
          "type": "appointment_status",
          "typeSchema": "public",
          "primaryKey": false,
          "notNull": true,
          "default": "'scheduled'"
        },
        "notes": {
          "name": "notes",
          "type": "text",
          "primaryKey": false,
          "notNull": false
        },
        "created_at": {
          "name": "created_at",
          "type": "timestamp",
          "primaryKey": false,
          "notNull": true,
          "default": "now()"
        },
        "updated_at": {
          "name": "updated_at",
          "type": "timestamp",
          "primaryKey": false,
          "notNull": true,
          "default": "now()"
        }
      },
      "indexes": {},
      "foreignKeys": {
        "appointments_client_id_users_id_fk": {
          "name": "appointments_client_id_users_id_fk",
          "tableFrom": "appointments",
          "tableTo": "users",
          "columnsFrom": [
            "client_id"
          ],
          "columnsTo": [
            "id"
          ],
          "onDelete": "no action",
          "onUpdate": "no action"
        },
        "appointments_barber_id_users_id_fk": {
          "name": "appointments_barber_id_users_id_fk",
          "tableFrom": "appointments",
          "tableTo": "users",
          "columnsFrom": [
            "barber_id"
          ],
          "columnsTo": [
            "id"
          ],
          "onDelete": "no action",
          "onUpdate": "no action"
        },
        "appointments_service_id_services_id_fk": {
          "name": "appointments_service_id_services_id_fk",
          "tableFrom": "appointments",
          "tableTo": "services",
          "columnsFrom": [
            "service_id"
          ],
          "columnsTo": [
            "id"
          ],
          "onDelete": "no action",
          "onUpdate": "no action"
        }
      },
      "compositePrimaryKeys": {},
      "uniqueConstraints": {},
      "policies": {},
      "checkConstraints": {},
      "isRLSEnabled": false
    },
    "public.barber_schedules": {
      "name": "barber_schedules",
      "schema": "",
      "columns": {
        "id": {
          "name": "id",
          "type": "uuid",
          "primaryKey": true,
          "notNull": true,
          "default": "gen_random_uuid()"
        },
        "barber_id": {
          "name": "barber_id",
          "type": "uuid",
          "primaryKey": false,
          "notNull": true
        },
        "day_of_week": {
          "name": "day_of_week",
          "type": "integer",
          "primaryKey": false,
          "notNull": true
        },
        "start_time": {
          "name": "start_time",
          "type": "time",
          "primaryKey": false,
          "notNull": true
        },
        "end_time": {
          "name": "end_time",
          "type": "time",
          "primaryKey": false,
          "notNull": true
        },
        "active": {
          "name": "active",
          "type": "boolean",
          "primaryKey": false,
          "notNull": true,
          "default": true
        }
      },
      "indexes": {},
      "foreignKeys": {
        "barber_schedules_barber_id_users_id_fk": {
          "name": "barber_schedules_barber_id_users_id_fk",
          "tableFrom": "barber_schedules",
          "tableTo": "users",
          "columnsFrom": [
            "barber_id"
          ],
          "columnsTo": [
            "id"
          ],
          "onDelete": "no action",
          "onUpdate": "no action"
        }
      },
      "compositePrimaryKeys": {},
      "uniqueConstraints": {},
      "policies": {},
      "checkConstraints": {},
      "isRLSEnabled": false
    },
    "public.services": {
      "name": "services",
      "schema": "",
      "columns": {
        "id": {
          "name": "id",
          "type": "uuid",
          "primaryKey": true,
          "notNull": true,
          "default": "gen_random_uuid()"
        },
        "name": {
          "name": "name",
          "type": "varchar(255)",
          "primaryKey": false,
          "notNull": true
        },
        "description": {
          "name": "description",
          "type": "text",
          "primaryKey": false,
          "notNull": false
        },
        "duration_minutes": {
          "name": "duration_minutes",
          "type": "integer",
          "primaryKey": false,
          "notNull": true
        },
        "price_in_cents": {
          "name": "price_in_cents",
          "type": "integer",
          "primaryKey": false,
          "notNull": true
        },
        "active": {
          "name": "active",
          "type": "boolean",
          "primaryKey": false,
          "notNull": true,
          "default": true
        },
        "created_at": {
          "name": "created_at",
          "type": "timestamp",
          "primaryKey": false,
          "notNull": true,
          "default": "now()"
        }
      },
      "indexes": {},
      "foreignKeys": {},
      "compositePrimaryKeys": {},
      "uniqueConstraints": {},
      "policies": {},
      "checkConstraints": {},
      "isRLSEnabled": false
    },
    "public.users": {
      "name": "users",
      "schema": "",
      "columns": {
        "id": {
          "name": "id",
          "type": "uuid",
          "primaryKey": true,
          "notNull": true,
          "default": "gen_random_uuid()"
        },
        "name": {
          "name": "name",
          "type": "varchar(255)",
          "primaryKey": false,
          "notNull": true
        },
        "email": {
          "name": "email",
          "type": "varchar(255)",
          "primaryKey": false,
          "notNull": true
        },
        "phone": {
          "name": "phone",
          "type": "varchar(20)",
          "primaryKey": false,
          "notNull": false
        },
        "role": {
          "name": "role",
          "type": "user_role",
          "typeSchema": "public",
          "primaryKey": false,
          "notNull": true,
          "default": "'client'"
        },
        "avatar_url": {
          "name": "avatar_url",
          "type": "text",
          "primaryKey": false,
          "notNull": false
        },
        "created_at": {
          "name": "created_at",
          "type": "timestamp",
          "primaryKey": false,
          "notNull": true,
          "default": "now()"
        },
        "updated_at": {
          "name": "updated_at",
          "type": "timestamp",
          "primaryKey": false,
          "notNull": true,
          "default": "now()"
        }
      },
      "indexes": {},
      "foreignKeys": {},
      "compositePrimaryKeys": {},
      "uniqueConstraints": {
        "users_email_unique": {
          "name": "users_email_unique",
          "nullsNotDistinct": false,
          "columns": [
            "email"
          ]
        }
      },
      "policies": {},
      "checkConstraints": {},
      "isRLSEnabled": false
    }
  },
  "enums": {
    "public.appointment_status": {
      "name": "appointment_status",
      "schema": "public",
      "values": [
        "scheduled",
        "confirmed",
        "in_progress",
        "completed",
        "cancelled",
        "no_show"
      ]
    },
    "public.user_role": {
      "name": "user_role",
      "schema": "public",
      "values": [
        "client",
        "barber",
        "admin"
      ]
    }
  },
  "schemas": {},
  "sequences": {},
  "roles": {},
  "policies": {},
  "views": {},
  "_meta": {
    "columns": {},
    "schemas": {},
    "tables": {}
  }
}